{"name":"JOUSTER 21 (WESTERLY)","images":[{"alt":"Jouster 21 (Westerly) photo on sailboatdata.com","src":"imagehelper.asp?file_id=4128","type":"photo"},{"alt":"Jouster 21 (Westerly) drawing on sailboatdata.com","src":"imagehelper.asp?file_id=9072","type":"drawing"}],"basics":{"hullType":"Fin w/transom hung rudder","rigType":"Fractional  Sloop","loa":{"feet":21,"meters":6.4},"lwl":{"feet":18.25,"meters":5.56},"beam":{"feet":7.5,"meters":2.29},"listedSa":{"feet":210,"meters":19.51},"draftMax":{"feet":3.5,"meters":1.07},"draftMin":null,"displacement":998,"ballast":431,"sailAreaDisp1":19.91,"balDisp":43.19,"dispLen":161.58,"designer":"Laurent Giles","builder":"Westerly Marine Ltd. (UK)","construction":"FG","balType":"Iron","firstBuilt":"1970","lastBuilt":"1975","numBuilt":146},"buildersPastPresent":[{"href":"view_builder.asp?builder_id=46","title":"Westerly Marine Construction Ltd."}],"designer":[{"href":"view_designer.asp?designer_id=123","title":"Jack Laurent Giles"}],"relatedLinks":[{"href":"http://www.westerly-owners.co.uk","title":"Westerly Owners Association"}],"notes":"Swing keel version: KU:2.33'; KD: 5.58'."}
