{"name":"FREEDOM 42","images":[{"alt":"Freedom 42 photo on sailboatdata.com","src":"imagehelper.asp?file_id=11198","type":"photo"},{"alt":"Freedom 42 drawing on sailboatdata.com","src":"imagehelper.asp?file_id=11182","type":"drawing"}],"basics":{"hullType":"Fin w/spade rudder","rigType":"Frac. Sloop (Free standing)","loa":{"feet":42,"meters":12.8},"lwl":{"feet":39.5,"meters":12.04},"beam":{"feet":13.42,"meters":4.09},"listedSa":{"feet":788,"meters":73.21},"draftMax":{"feet":6,"meters":1.83},"draftMin":null,"displacement":10886,"ballast":null,"sailAreaDisp1":15.21,"balDisp":null,"dispLen":173.85,"designer":"Gary Mull","builder":"Tillotson Pearson Inc, (USA)","construction":"FG","balType":"Lead","firstBuilt":"1987","lastBuilt":null,"numBuilt":null},"rigSail":{"i_ig":{"feet":38,"meters":11.58},"j":{"feet":13.83,"meters":4.22},"p":{"feet":56.83,"meters":17.32},"e":{"feet":18.5,"meters":5.64},"py":null,"ey":null,"isp":null,"spl_tps":null,"saFore":{"feet":262.77,"meters":24.41},"saMain":{"feet":525.68,"meters":48.84},"sailArea":{"feet":788.45,"meters":73.25},"sailAreaDisp2":15.22,"estForestayLength":{"feet":40.44,"meters":12.33}},"buildersPastPresent":[{"href":"view_builder.asp?builder_id=223","title":"Freedom Yachts"}],"designer":[{"href":"view_designer.asp?designer_id=19","title":"Gary Mull"}]}
