{"name":"O'DAY 31","images":[{"alt":"O'Day 31 photo on sailboatdata.com","src":"imagehelper.asp?file_id=3556","type":"photo"},{"alt":"O'Day 31 layout drawing on sailboatdata.com","src":"imagehelper.asp?file_id=10555","type":"drawing"}],"basics":{"hullType":"Fin w/spade rudder","rigType":"Masthead Sloop","loa":{"feet":30.08,"meters":9.17},"lwl":{"feet":25.88,"meters":7.89},"beam":{"feet":10.75,"meters":3.28},"listedSa":{"feet":436,"meters":40.5},"draftMax":{"feet":5.25,"meters":1.6},"draftMin":null,"displacement":4581,"ballast":1724,"sailAreaDisp1":14.98,"balDisp":37.63,"dispLen":260.12,"designer":"C. Raymond Hunt Associates","builder":"O'Day Corp. (USA)","construction":"FG","balType":null,"firstBuilt":"1985","lastBuilt":"1988","numBuilt":150},"auxPower":{"make":"Universal","model":null,"type":"Diesel","hp":"14"},"tanks":{"water":"25 gals. /  95 ltrs.","fuel":"25 gals. /  95 ltrs."},"rigSail":{"i_ig":{"feet":39.75,"meters":12.12},"j":{"feet":13.25,"meters":4.04},"p":{"feet":33.75,"meters":10.29},"e":{"feet":10.25,"meters":3.12},"py":null,"ey":null,"isp":null,"spl_tps":null,"saFore":{"feet":263.34,"meters":24.46},"saMain":{"feet":172.97,"meters":16.07},"sailArea":{"feet":436.31,"meters":40.53},"sailAreaDisp2":14.99,"estForestayLength":{"feet":41.9,"meters":12.77}},"buildersPastPresent":[{"href":"view_builder.asp?builder_id=51","title":"O'Day Corp."},{"href":"view_builder.asp?builder_id=302","title":"Bangor Punta Corp."}],"designer":[{"href":"view_designer.asp?designer_id=6","title":"Raymond Hunt (C.R. Hunt & Assoc.)"}],"seeAlso":{"relatedBoat":{"href":"viewrecord.asp?class_id=1334","title":"O'DAY 30"}},"notes":"Updated/extended version of O'DAY 30/RANGER 30. (1977?)\r\nAvailable with shoal draft keel. Draft: 4.0'."}
