{"name":"O'DAY 22 CB MH","images":[],"basics":{"hullType":"Keel/Cbrd.","rigType":"Masthead Sloop","loa":{"feet":22,"meters":6.71},"lwl":{"feet":18.92,"meters":5.77},"beam":{"feet":7.17,"meters":2.19},"listedSa":{"feet":190,"meters":17.65},"draftMax":{"feet":4.7,"meters":1.43},"draftMin":{"feet":1.3,"meters":0.4},"displacement":1194,"ballast":272,"sailAreaDisp1":15.99,"balDisp":22.78,"dispLen":173.49,"designer":"C. Raymond Hunt","builder":"O'Day Corp (USA)","construction":"FG","balType":null,"firstBuilt":"1973","lastBuilt":"1983","numBuilt":null},"rigSail":{"i_ig":{"feet":24,"meters":7.32},"j":{"feet":9,"meters":2.74},"p":{"feet":20.5,"meters":6.25},"e":{"feet":8,"meters":2.44},"py":{"feet":4.7,"meters":1.43},"ey":null,"isp":null,"spl_tps":null,"saFore":{"feet":108,"meters":10.03},"saMain":{"feet":82,"meters":7.62},"sailArea":{"feet":190,"meters":17.65},"sailAreaDisp2":15.99,"estForestayLength":{"feet":25.63,"meters":7.81}},"notes":"Dimensions for O'DAY 22 keel/cb version with masthead rig.\r\nSee O'DAY 22 for more information."}
