{"name":"ERICSON 34T","images":[{"alt":"Ericson 34T photo on sailboatdata.com","src":"imagehelper.asp?file_id=3303","type":"photo"},{"alt":"Ericson 34T drawing on sailboatdata.com","src":"imagehelper.asp?file_id=1904","type":"drawing"}],"basics":{"hullType":"Fin w/spade rudder","rigType":"Masthead Sloop","loa":{"feet":33.67,"meters":10.26},"lwl":{"feet":26.42,"meters":8.05},"beam":{"feet":10.92,"meters":3.33},"listedSa":{"feet":504,"meters":46.82},"draftMax":{"feet":5.92,"meters":1.8},"draftMin":null,"displacement":5262,"ballast":2268,"sailAreaDisp1":15.79,"balDisp":43.1,"dispLen":280.81,"designer":"Bruce King","builder":"Ericson Yachts (USA)","construction":"FG","balType":"Lead","firstBuilt":"1978","lastBuilt":null,"numBuilt":null},"rigSail":{"i_ig":{"feet":43,"meters":13.11},"j":{"feet":13.83,"meters":4.22},"p":{"feet":38,"meters":11.58},"e":{"feet":10.86,"meters":3.31},"py":null,"ey":null,"isp":null,"spl_tps":null,"saFore":{"feet":297.35,"meters":27.62},"saMain":{"feet":206.34,"meters":19.17},"sailArea":{"feet":503.69,"meters":46.79},"sailAreaDisp2":15.78,"estForestayLength":{"feet":45.17,"meters":13.77}},"buildersPastPresent":[{"href":"view_builder.asp?builder_id=75","title":"Ericson Yachts (USA)"}],"designer":[{"href":"view_designer.asp?designer_id=127","title":"Bruce King"}],"seeAlso":{"relatedBoat":{"href":"viewrecord.asp?class_id=1876","title":"ERICSON 34X"}},"notes":"The ''T'' is for the trunk cabin version of this IOR influenced ERICSON 34. See ERICSON 34 X which is the flush deck version.\r\n\r\nTALL RIG:\r\nI: 45.00' / 13.72m\r\nJ: 13.83' / 4.22m\r\nP: 39.00' / 11.89m\r\nE: 11.22' / 3.42m\r\nTot. SA (100%): 529.97 ft2 / 49.23 m2"}
