{"name":"PRAIRIE 32","images":[],"basics":{"hullType":"Long keel w/trans. hung rudder","rigType":"Cutter","loa":{"feet":31.67,"meters":9.65},"lwl":{"feet":25.68,"meters":7.83},"beam":{"feet":11.12,"meters":3.39},"listedSa":{"feet":578,"meters":53.7},"draftMax":{"feet":4.5,"meters":1.37},"draftMin":null,"displacement":7847,"ballast":3175,"sailAreaDisp1":13.88,"balDisp":40.46,"dispLen":456.05,"designer":"George S. Hawn, Jr","builder":"Prairie Boat Works (USA)","construction":"FG","balType":"Lead","firstBuilt":"1976","lastBuilt":null,"numBuilt":35},"auxPower":{"make":"Yanmar","model":null,"type":"Diesel","hp":null},"tanks":{"water":"35 gals. /  132 ltrs.","fuel":"35 gals. /  132 ltrs."},"rigSail":{"i_ig":{"feet":44.2,"meters":13.47},"j":{"feet":15,"meters":4.57},"p":{"feet":39.5,"meters":12.04},"e":{"feet":12.5,"meters":3.81},"py":null,"ey":null,"isp":null,"spl_tps":null,"saFore":{"feet":331.5,"meters":30.8},"saMain":{"feet":246.88,"meters":22.93},"sailArea":{"feet":578.38,"meters":53.73},"sailAreaDisp2":13.89,"estForestayLength":{"feet":46.68,"meters":14.23}},"buildersPastPresent":[{"href":"view_builder.asp?builder_id=494","title":"Prairie Boat Works (USA)"}],"notes":"Prairie Boat Works was located in Clearwater, FL, USA."}
