{"name":"ANDREWS 39","images":[{"alt":"Andrews 39 photo on sailboatdata.com","src":"imagehelper.asp?file_id=984","type":"photo"}],"basics":{"hullType":"Fin w/spade rudder","rigType":"Fractional  Sloop","loa":{"feet":39.42,"meters":12.02},"lwl":{"feet":32.42,"meters":9.88},"beam":{"feet":12.42,"meters":3.79},"listedSa":{"feet":820,"meters":76.18},"draftMax":{"feet":6.67,"meters":2.03},"draftMin":null,"displacement":5761,"ballast":2722,"sailAreaDisp1":24.19,"balDisp":47.25,"dispLen":166.39,"designer":"Alan Andrews","builder":"Dencho Marine (USA)","construction":"FG","balType":null,"firstBuilt":"1983","lastBuilt":null,"numBuilt":2},"rigSail":{"i_ig":{"feet":47.9,"meters":14.6},"j":{"feet":13.83,"meters":4.22},"p":{"feet":52.16,"meters":15.9},"e":{"feet":18.73,"meters":5.71},"py":null,"ey":null,"isp":null,"spl_tps":null,"saFore":{"feet":331.23,"meters":30.77},"saMain":{"feet":488.48,"meters":45.38},"sailArea":{"feet":819.71,"meters":76.15},"sailAreaDisp2":24.18,"estForestayLength":{"feet":49.86,"meters":15.2}},"buildersPastPresent":[{"href":"view_builder.asp?builder_id=127","title":"Dencho Marine"}],"designer":[{"href":"view_designer.asp?designer_id=77","title":"Alan Andrews"}],"notes":"Prototype was 'Allegiance', 1st in class and 2nd over all at the 1984 SORC. Tooling was created for production but only one additional boat was built.\r\nThanks to 'SPB' for providing additional information."}
