{"name":"THOMAS 35","images":[{"alt":"Thomas 35 photo on sailboatdata.com","src":"imagehelper.asp?file_id=7355","type":"photo"},{"alt":"Thomas 35 drawing on sailboatdata.com","src":"imagehelper.asp?file_id=9184","type":"drawing"}],"basics":{"hullType":"Fin w/spade rudder","rigType":"Masthead Sloop","loa":{"feet":35.42,"meters":10.8},"lwl":{"feet":30.5,"meters":9.3},"beam":{"feet":11.5,"meters":3.51},"listedSa":{"feet":702,"meters":65.22},"draftMax":{"feet":6.83,"meters":2.08},"draftMin":null,"displacement":4445,"ballast":2019,"sailAreaDisp1":24.61,"balDisp":45.42,"dispLen":154.2,"designer":"Graham & Schlageter","builder":"Thomas Marine Inc./Tartan Marine (USA)","construction":"FG","balType":"Lead","firstBuilt":"1988","lastBuilt":null,"numBuilt":null},"auxPower":{"make":"Yanmar","model":"3GM","type":"Diesel","hp":"27"},"tanks":{"water":"35 gals. /  132 ltrs.","fuel":"20 gals. /  76 ltrs."},"rigSail":{"i_ig":{"feet":48,"meters":14.63},"j":{"feet":14.25,"meters":4.34},"p":{"feet":48,"meters":14.63},"e":{"feet":15,"meters":4.57},"py":null,"ey":null,"isp":null,"spl_tps":null,"saFore":{"feet":342,"meters":31.77},"saMain":{"feet":360,"meters":33.44},"sailArea":{"feet":702,"meters":65.22},"sailAreaDisp2":24.61,"estForestayLength":{"feet":50.07,"meters":15.26}},"buildersPastPresent":[{"href":"view_builder.asp?builder_id=156","title":"Tartan Marine"}],"designer":[{"href":"view_designer.asp?designer_id=94","title":"Graham & Schlageter"}],"notes":"Also promoted as T-35."}
