{"name":"FRERS 39","images":[{"alt":"Frers 39 (1974) drawing on sailboatdata.com","src":"imagehelper.asp?file_id=7310","type":"drawing"}],"basics":{"hullType":"Fin with rudder on skeg","rigType":"Masthead Sloop","loa":{"feet":38.75,"meters":11.81},"lwl":{"feet":31.5,"meters":9.6},"beam":{"feet":12.5,"meters":3.81},"listedSa":{"feet":638,"meters":59.27},"draftMax":{"feet":6.33,"meters":1.93},"draftMin":null,"displacement":7847,"ballast":3856,"sailAreaDisp1":15.32,"balDisp":49.14,"dispLen":247.1,"designer":"German Frers","builder":"Frers & Cibils (ARG)","construction":"FG","balType":null,"firstBuilt":"1974","lastBuilt":null,"numBuilt":null},"rigSail":{"i_ig":{"feet":48.6,"meters":14.81},"j":{"feet":15.8,"meters":4.82},"p":{"feet":42.8,"meters":13.05},"e":{"feet":11.8,"meters":3.6},"py":null,"ey":null,"isp":null,"spl_tps":null,"saFore":{"feet":383.94,"meters":35.67},"saMain":{"feet":252.52,"meters":23.46},"sailArea":{"feet":636.46,"meters":59.13},"sailAreaDisp2":15.28,"estForestayLength":{"feet":51.1,"meters":15.58}},"designer":[{"href":"view_designer.asp?designer_id=23","title":"German Frers"}]}
