{"name":"SCHOCK 35 WK","images":[],"basics":{"hullType":"Wing Keel","rigType":"Masthead Sloop","loa":{"feet":35,"meters":10.67},"lwl":{"feet":29.5,"meters":8.99},"beam":{"feet":11.75,"meters":3.58},"listedSa":{"feet":639,"meters":59.36},"draftMax":{"feet":5.33,"meters":1.62},"draftMin":null,"displacement":4309,"ballast":1814,"sailAreaDisp1":22.87,"balDisp":42.1,"dispLen":165.2,"designer":"Shad Turner","builder":"W. D. Schock Corp.(USA)","construction":"FG","balType":null,"firstBuilt":"1984","lastBuilt":null,"numBuilt":null},"rigSail":{"i_ig":{"feet":49,"meters":14.94},"j":{"feet":13.75,"meters":4.19},"p":{"feet":44,"meters":13.41},"e":{"feet":13.75,"meters":4.19},"py":null,"ey":null,"isp":null,"spl_tps":null,"saFore":{"feet":336.88,"meters":31.3},"saMain":{"feet":302.5,"meters":28.1},"sailArea":{"feet":639.38,"meters":59.4},"sailAreaDisp2":22.88,"estForestayLength":{"feet":50.89,"meters":15.51}}}
