{"name":"FIRST 38 VSD TM (BENETEAU)","images":[],"basics":{"hullType":"Fin w/spade rudder","rigType":"Masthead Sloop","loa":{"feet":38.5,"meters":11.73},"lwl":{"feet":33.83,"meters":10.31},"beam":{"feet":12.83,"meters":3.91},"listedSa":{"feet":667,"meters":61.96},"draftMax":{"feet":4.9,"meters":1.49},"draftMin":null,"displacement":7101,"ballast":null,"sailAreaDisp1":17.12,"balDisp":null,"dispLen":180.51,"designer":"Beret","builder":"Beneteau (FRA)","construction":"FG","balType":null,"firstBuilt":"1984","lastBuilt":null,"numBuilt":null},"rigSail":{"i_ig":{"feet":50.2,"meters":15.3},"j":{"feet":14.42,"meters":4.4},"p":{"feet":44.3,"meters":13.5},"e":{"feet":13.8,"meters":4.21},"py":null,"ey":null,"isp":null,"spl_tps":null,"saFore":{"feet":361.94,"meters":33.62},"saMain":{"feet":305.67,"meters":28.4},"sailArea":{"feet":667.61,"meters":62.02},"sailAreaDisp2":17.13,"estForestayLength":{"feet":52.23,"meters":15.92}},"notes":"Very shallow draft version."}
