{"name":"NASSAU 45","images":[{"alt":"Nassau 45 photo on sailboatdata.com","src":"imagehelper.asp?file_id=1284","type":"photo"}],"basics":{"hullType":"Fin w/spade rudder","rigType":"Masthead Sloop","loa":{"feet":45.92,"meters":14},"lwl":{"feet":34.58,"meters":10.54},"beam":{"feet":12.75,"meters":3.89},"listedSa":{"feet":799,"meters":74.23},"draftMax":{"feet":5.8,"meters":1.77},"draftMin":null,"displacement":9639,"ballast":4023,"sailAreaDisp1":16.73,"balDisp":41.74,"dispLen":229.42,"designer":"Robert Perry","builder":"Angel Marine (TAIWAN)","construction":"FG","balType":null,"firstBuilt":"1984","lastBuilt":null,"numBuilt":null},"auxPower":{"make":"Perkins","model":null,"type":"Diesel","hp":"40"},"tanks":{"water":"160 gals. /  606 ltrs.","fuel":"70 gals. /  265 ltrs."},"rigSail":{"i_ig":{"feet":50.5,"meters":15.39},"j":{"feet":16.5,"meters":5.03},"p":{"feet":45,"meters":13.72},"e":{"feet":17,"meters":5.18},"py":null,"ey":null,"isp":null,"spl_tps":null,"saFore":{"feet":416.63,"meters":38.7},"saMain":{"feet":382.5,"meters":35.53},"sailArea":{"feet":799.13,"meters":74.24},"sailAreaDisp2":16.73,"estForestayLength":{"feet":53.13,"meters":16.19}},"designer":[{"href":"view_designer.asp?designer_id=46","title":"Robert Perry"}],"notes":"A modified version of the NORDIC 44."}
