{"name":"FIRST 53F5 (BENETEAU)","images":[{"alt":"First 53f5 (Beneteau) photo on sailboatdata.com","src":"imagehelper.asp?file_id=7510","type":"photo"},{"alt":"First 53F5 (Beneteau) drawing on sailboatdata.com","src":"imagehelper.asp?file_id=7509","type":"drawing"}],"basics":{"hullType":"Fin w/bulb & spade rudder","rigType":"Masthead Sloop","loa":{"feet":52.17,"meters":15.9},"lwl":{"feet":43.33,"meters":13.21},"beam":{"feet":14.75,"meters":4.5},"listedSa":{"feet":1059,"meters":98.38},"draftMax":{"feet":8.08,"meters":2.46},"draftMin":null,"displacement":14000,"ballast":4300,"sailAreaDisp1":17.29,"balDisp":30.71,"dispLen":169.37,"designer":"Bruce Farr","builder":"Beneteau","construction":"FG","balType":null,"firstBuilt":"1990","lastBuilt":null,"numBuilt":null},"tanks":{"water":"105 gals. /  397 ltrs.","fuel":"119 gals. /  450 ltrs."},"rigSail":{"i_ig":{"feet":62.25,"meters":18.97},"j":{"feet":17.5,"meters":5.33},"p":{"feet":55.42,"meters":16.89},"e":{"feet":18.58,"meters":5.66},"py":null,"ey":null,"isp":null,"spl_tps":null,"saFore":{"feet":544.69,"meters":50.6},"saMain":{"feet":514.85,"meters":47.83},"sailArea":{"feet":1,"meters":98.43},"sailAreaDisp2":17.3,"estForestayLength":{"feet":64.66,"meters":19.71}},"buildersPastPresent":[{"href":"view_builder.asp?builder_id=80","title":"Beneteau"}],"designer":[{"href":"view_designer.asp?designer_id=17","title":"Bruce Farr"}],"notes":"Also called BENETEAU 53F5. \r\nDouble aft cabin and four cabin versions and shoal draft (wing keel) available(draft: 6.25'/1.9m)."}
