{"name":"HANSE 311","images":[{"alt":"Hanse 311 photo on sailboatdata.com","src":"imagehelper.asp?file_id=10794","type":"photo"},{"alt":"Hanse 311 drawing on sailboatdata.com","src":"imagehelper.asp?file_id=1677","type":"drawing"}],"basics":{"hullType":"Fin w/bulb & spade rudder","rigType":"Fractional  Sloop","loa":{"feet":29.49,"meters":8.99},"lwl":{"feet":26.48,"meters":8.07},"beam":{"feet":10.5,"meters":3.2},"listedSa":{"feet":540,"meters":50.17},"draftMax":{"feet":5.74,"meters":1.75},"draftMin":null,"displacement":3860,"ballast":1250,"sailAreaDisp1":20.8,"balDisp":32.38,"dispLen":204.61,"designer":"Judel/Vrolijk","builder":"HANSE Yachts (GER)","construction":"FG","balType":null,"firstBuilt":"2000","lastBuilt":"2006","numBuilt":null},"auxPower":{"make":"Volvo Penta","model":"2020 sailrive","type":"Diesel","hp":"19"},"tanks":{"water":"35 gals. /  132 ltrs.","fuel":"20 gals. /  76 ltrs."},"buildersPastPresent":[{"href":"view_builder.asp?builder_id=166","title":"Hanse Yachts"}],"designer":[{"href":"view_designer.asp?designer_id=18","title":"Judel/Vrolijk & Co."}],"notes":"Shoal draft: 4.5'/1.4m"}
