{"name":"DIVA 45","images":[{"alt":"Diva 45 photo on sailboatdata.com","src":"imagehelper.asp?file_id=2774","type":"photo"}],"basics":{"hullType":"Fin w/spade rudder","rigType":"Fractional  Sloop","loa":{"feet":41.17,"meters":12.55},"lwl":{"feet":36.58,"meters":11.15},"beam":{"feet":12.67,"meters":3.86},"listedSa":{"feet":880,"meters":81.75},"draftMax":{"feet":7.7,"meters":2.35},"draftMin":null,"displacement":7000,"ballast":3200,"sailAreaDisp1":22.8,"balDisp":45.71,"dispLen":140.75,"designer":"Bernt Lindquist","builder":"Fabola Boats (SWE)","construction":"FG","balType":null,"firstBuilt":"1985","lastBuilt":"1990","numBuilt":null},"auxPower":{"make":"Yanmar","model":"4JHE","type":"Diesel","hp":null},"rigSail":{"i_ig":{"feet":51.51,"meters":15.7},"j":{"feet":15.42,"meters":4.7},"p":{"feet":53.48,"meters":16.3},"e":{"feet":18.05,"meters":5.5},"py":null,"ey":null,"isp":null,"spl_tps":null,"saFore":{"feet":397.14,"meters":36.89},"saMain":{"feet":482.66,"meters":44.84},"sailArea":{"feet":879.8,"meters":81.73},"sailAreaDisp2":22.79,"estForestayLength":{"feet":53.77,"meters":16.39}},"buildersPastPresent":[{"href":"view_builder.asp?builder_id=204","title":"Fabola Boats (SWE)"}],"designer":[{"href":"view_designer.asp?designer_id=207","title":"Bernt Lindquist"}],"notes":"The similar but updated DIVA 451 was introduced in 1990."}
