{"name":"H-323","images":[{"alt":"H-323 photo on sailboatdata.com","src":"imagehelper.asp?file_id=2617","type":"photo"}],"basics":{"hullType":"Fin w/spade rudder","rigType":"Fractional  Sloop","loa":{"feet":32.32,"meters":9.85},"lwl":{"feet":25.59,"meters":7.8},"beam":{"feet":8.4,"meters":2.56},"listedSa":{"feet":384,"meters":35.67},"draftMax":{"feet":4.75,"meters":1.45},"draftMin":null,"displacement":2800,"ballast":1200,"sailAreaDisp1":18.31,"balDisp":42.86,"dispLen":164.45,"designer":"Hans Groop","builder":"Artekno (FIN)","construction":"FG","balType":null,"firstBuilt":"1980","lastBuilt":"1990","numBuilt":null},"auxPower":{"make":"Yanmar","model":"1GM","type":"Diesel","hp":null},"rigSail":{"i_ig":{"feet":30.67,"meters":9.35},"j":{"feet":10.84,"meters":3.3},"p":{"feet":35.46,"meters":10.81},"e":{"feet":12.31,"meters":3.75},"py":null,"ey":null,"isp":null,"spl_tps":null,"saFore":{"feet":166.23,"meters":15.44},"saMain":{"feet":218.26,"meters":20.28},"sailArea":{"feet":384.49,"meters":35.72},"sailAreaDisp2":18.34,"estForestayLength":{"feet":32.53,"meters":9.91}},"buildersPastPresent":[{"href":"view_builder.asp?builder_id=387","title":"Artekno OY (FIN)"}],"designer":[{"href":"view_designer.asp?designer_id=215","title":"Hans Groop"}]}
