{"name":"OYSTER 55","images":[{"alt":"Oyster 55 photo on sailboatdata.com","src":"imagehelper.asp?file_id=2189","type":"photo"}],"basics":{"hullType":"Fin with rudder on skeg","rigType":"Cutter","loa":{"feet":56.25,"meters":17.15},"lwl":{"feet":45.43,"meters":13.85},"beam":{"feet":15.75,"meters":4.8},"listedSa":null,"draftMax":{"feet":7.5,"meters":2.29},"draftMin":null,"displacement":23134,"ballast":6060,"sailAreaDisp1":null,"balDisp":26.2,"dispLen":242.83,"designer":"Holman  & Pyle","builder":"Oyster Marine Ltd. (UK)","construction":"FG","balType":null,"firstBuilt":"1986","lastBuilt":null,"numBuilt":55},"auxPower":{"make":"Perkins","model":null,"type":"Diesel","hp":"80"},"tanks":{"water":"290 gals. /  1098 ltrs.","fuel":"158 gals. /  598 ltrs."},"buildersPastPresent":[{"href":"view_builder.asp?builder_id=238","title":"Oyster Marine"}],"designer":[{"href":"view_designer.asp?designer_id=115","title":"Kim Holman"}],"notes":"Earlier boats were called the OYSTER 53."}
