{"name":"F-9A","images":[{"alt":"F-9A drawing on sailboatdata.com","src":"imagehelper.asp?file_id=2412","type":"drawing"}],"basics":{"hullType":"Trimaran Dbrd.","rigType":"Fractional  Sloop","loa":{"feet":30.83,"meters":9.4},"lwl":{"feet":30,"meters":9.14},"beam":{"feet":22.42,"meters":6.83},"listedSa":null,"draftMax":{"feet":5.5,"meters":1.68},"draftMin":{"feet":1.33,"meters":0.41},"displacement":1588,"ballast":null,"sailAreaDisp1":null,"balDisp":null,"dispLen":57.87,"designer":"Ian Farrier","builder":"various","construction":"FG or strip plank","balType":null,"firstBuilt":"1991","lastBuilt":null,"numBuilt":300},"designer":[{"href":"view_designer.asp?designer_id=170","title":"Ian Farrier"}]}
