{"name":"NORTH AMERICAN 22","images":[],"basics":{"hullType":"Long Keel","rigType":"Masthead Sloop","loa":{"feet":22,"meters":6.71},"lwl":{"feet":16,"meters":4.88},"beam":{"feet":7,"meters":2.13},"listedSa":null,"draftMax":{"feet":3.08,"meters":0.94},"draftMin":null,"displacement":1452,"ballast":699,"sailAreaDisp1":null,"balDisp":48.14,"dispLen":348.77,"designer":"Carl Alberg","builder":"North American Fiberglass Moulding(CAN)","construction":"FG","balType":null,"firstBuilt":"1963","lastBuilt":null,"numBuilt":null},"rigSail":{"i_ig":{"feet":27.8,"meters":8.47},"j":{"feet":8.8,"meters":2.68},"p":{"feet":24,"meters":7.32},"e":{"feet":9.5,"meters":2.9},"py":null,"ey":null,"isp":null,"spl_tps":null,"saFore":{"feet":122.32,"meters":11.36},"saMain":{"feet":114,"meters":10.59},"sailArea":{"feet":236.32,"meters":21.95},"sailAreaDisp2":17.46,"estForestayLength":{"feet":29.16,"meters":8.89}},"designer":[{"href":"view_designer.asp?designer_id=16","title":"Carl Alberg"}],"seeAlso":{"relatedBoat":{"href":"viewrecord.asp?class_id=318","title":"ALBERG 22"}},"notes":"Also known as the ALBERG 22 and DOUGLAS 22."}
