{"name":"PUMA 38","images":[],"basics":{"hullType":"Fin Keel","rigType":"Masthead Sloop","loa":{"feet":38.06,"meters":11.6},"lwl":{"feet":29.53,"meters":9},"beam":{"feet":11.81,"meters":3.6},"listedSa":{"feet":834,"meters":77.48},"draftMax":{"feet":6.56,"meters":2},"draftMin":null,"displacement":7000,"ballast":3000,"sailAreaDisp1":21.61,"balDisp":42.86,"dispLen":267.54,"designer":"Alberto Cabal","builder":"Nao Glass (ESP)","construction":"FG","balType":null,"firstBuilt":"1976","lastBuilt":null,"numBuilt":null},"buildersPastPresent":[{"href":"view_builder.asp?builder_id=280","title":"Puma Yachts (Nao-Glass)(ESP)"}],"designer":[{"href":"view_designer.asp?designer_id=394","title":"Alberto Cabal"}]}
