{"name":"FIRST 36.7 (BENETEAU)","images":[{"alt":"First 36.7 photo on sailboatdata.com","src":"imagehelper.asp?file_id=6906","type":"photo"},{"alt":"First 36.7 drawing on sailboatdata.com","src":"imagehelper.asp?file_id=6905","type":"drawing"}],"basics":{"hullType":"Fin w/bulb & spade rudder","rigType":"Fractional  Sloop","loa":{"feet":36.08,"meters":11},"lwl":{"feet":30.25,"meters":9.22},"beam":{"feet":11.33,"meters":3.45},"listedSa":{"feet":657,"meters":61.04},"draftMax":{"feet":7.17,"meters":2.19},"draftMin":null,"displacement":5804,"ballast":1700,"sailAreaDisp1":19.28,"balDisp":29.29,"dispLen":206.36,"designer":"Farr Yacht Design","builder":"Beneteau (USA)","construction":"FG","balType":null,"firstBuilt":"2000","lastBuilt":null,"numBuilt":800},"auxPower":{"make":"Volvo","model":null,"type":"Diesel","hp":"29"},"tanks":{"water":"79 gals. /  299 ltrs.","fuel":"21 gals. /  79 ltrs."},"rigSail":{"i_ig":{"feet":46.42,"meters":14.15},"j":{"feet":13.04,"meters":3.97},"p":{"feet":45.44,"meters":13.85},"e":{"feet":15.58,"meters":4.75},"py":null,"ey":null,"isp":null,"spl_tps":null,"saFore":{"feet":302.66,"meters":28.12},"saMain":{"feet":353.98,"meters":32.88},"sailArea":{"feet":656.64,"meters":61},"sailAreaDisp2":19.27,"estForestayLength":{"feet":48.22,"meters":14.7},"mastHeightFromDwl":"55.75' /  16.99m"},"buildersPastPresent":[{"href":"view_builder.asp?builder_id=45","title":"Beneteau USA"},{"href":"view_builder.asp?builder_id=80","title":"Beneteau"}],"designer":[{"href":"view_designer.asp?designer_id=17","title":"Bruce Farr"}],"relatedLinks":[{"href":"http://www.beneteaufirst367.org","title":"First 36.7 Association"}],"notes":"Shallow draft version: 5.2'/1.58m.\r\nFarr design #446."}
