{"name":"C&C 26 WAVE","images":[{"alt":"C&C 26 Wave drawing on sailboatdata.com","src":"imagehelper.asp?file_id=3691","type":"drawing"}],"basics":{"hullType":"Wing Keel","rigType":"Masthead Sloop","loa":{"feet":26.67,"meters":8.13},"lwl":{"feet":23,"meters":7.01},"beam":{"feet":9.25,"meters":2.82},"listedSa":{"feet":292,"meters":27.13},"draftMax":{"feet":2.92,"meters":0.89},"draftMin":null,"displacement":2132,"ballast":771,"sailAreaDisp1":16.7,"balDisp":36.16,"dispLen":172.45,"designer":"Bob Ball","builder":"C&C Yachts","construction":"FG","balType":"Iron","firstBuilt":"1988","lastBuilt":null,"numBuilt":null},"auxPower":{"make":"Universal","model":"M-12","type":"Diesel","hp":null},"tanks":{"water":"20 gals. /  76 ltrs.","fuel":"11 gals. /  42 ltrs."},"buildersPastPresent":[{"href":"view_builder.asp?builder_id=10","title":"C&C Yachts"}],"designer":[{"href":"view_designer.asp?designer_id=113","title":"Cuthbertson & Cassian"},{"href":"view_designer.asp?designer_id=243","title":"Robert Ball"}],"relatedLinks":[{"href":"http://www.cncphotoalbum.com","title":"C&C Yachts photo album"}],"seeAlso":{"relatedBoat":{"href":"viewrecord.asp?class_id=3009","title":"C&C 27 MK V"}},"notes":"The WAVE model is based on the C&C 27-5 but with a winged keel and shorter rig.\r\nThanks to 'forensicsail' for providing corrections."}
