{"name":"DEB 33","images":[{"alt":"Deb 33 drawing on sailboatdata.com","src":"imagehelper.asp?file_id=9091","type":"drawing"}],"basics":{"hullType":"Keel/Cbrd.","rigType":"Masthead Sloop","loa":{"feet":33.42,"meters":10.19},"lwl":{"feet":24,"meters":7.32},"beam":{"feet":10.33,"meters":3.15},"listedSa":{"feet":490,"meters":45.52},"draftMax":{"feet":6.58,"meters":2.01},"draftMin":{"feet":3.58,"meters":1.09},"displacement":5670,"ballast":2359,"sailAreaDisp1":14.61,"balDisp":41.6,"dispLen":403.67,"designer":"Sparkman & Stephens","builder":"Tyler Mouldings/Deacons Boatyard Ltd. (UK)","construction":"FG","balType":null,"firstBuilt":"1969","lastBuilt":null,"numBuilt":50},"auxPower":{"make":"Volvo","model":"MD2B","type":"Diesel","hp":null},"tanks":{"water":"120 gals. /  454 ltrs.","fuel":"18 gals. /  68 ltrs."},"rigSail":{"i_ig":{"feet":40,"meters":12.19},"j":{"feet":13.5,"meters":4.11},"p":{"feet":34.5,"meters":10.52},"e":{"feet":12.75,"meters":3.89},"py":null,"ey":null,"isp":null,"spl_tps":null,"saFore":{"feet":270,"meters":25.08},"saMain":{"feet":219.94,"meters":20.43},"sailArea":{"feet":489.94,"meters":45.52},"sailAreaDisp2":14.61,"estForestayLength":{"feet":42.22,"meters":12.87}},"buildersPastPresent":[{"href":"view_builder.asp?builder_id=174","title":"Tyler Boat Co. Ltd. (UK)"},{"href":"view_builder.asp?builder_id=235","title":"Deacons Boat Yard Ltd."}],"designer":[{"href":"view_designer.asp?designer_id=12","title":"Sparkman & Stephens"}],"notes":"S&S design #1873.\r\nMolded by Tyler Boat Co, finished by Deacons Boatyard. A fixed keel version was also available."}
