{"name":"WINGA 78","images":[{"alt":"Winga 78 photo on sailboatdata.com","src":"imagehelper.asp?file_id=4045","type":"photo"}],"basics":{"hullType":"Fin Keel","rigType":"Fractional  Sloop","loa":{"feet":25.75,"meters":7.85},"lwl":{"feet":19.82,"meters":6.04},"beam":{"feet":9.68,"meters":2.95},"listedSa":null,"draftMax":{"feet":4.1,"meters":1.25},"draftMin":null,"displacement":3100,"ballast":1000,"sailAreaDisp1":null,"balDisp":32.26,"dispLen":391.85,"designer":"Rolf Eliason","builder":"Winga Marine (SWE)","construction":"FG","balType":null,"firstBuilt":"1976","lastBuilt":null,"numBuilt":null},"auxPower":{"make":"Volvo","model":null,"type":"Diesel","hp":null},"tanks":{"water":"4 gals. /  15 ltrs.","fuel":null},"buildersPastPresent":[{"href":"view_builder.asp?builder_id=189","title":"Winga Marin"}],"designer":[{"href":"view_designer.asp?designer_id=320","title":"Rolf E. Eliasson"}]}
