{"name":"SOUTH COAST 25","images":[{"alt":"South Coast 25 photo on sailboatdata.com","src":"imagehelper.asp?file_id=5610","type":"photo"},{"alt":"South Coast 25 drawing on sailboatdata.com","src":"imagehelper.asp?file_id=5609","type":"drawing"}],"basics":{"hullType":"Fin w/spade rudder","rigType":"Masthead Sloop","loa":{"feet":25,"meters":7.62},"lwl":{"feet":20.5,"meters":6.25},"beam":{"feet":7.5,"meters":2.29},"listedSa":{"feet":299,"meters":27.78},"draftMax":{"feet":3.5,"meters":1.07},"draftMin":null,"displacement":1905,"ballast":816,"sailAreaDisp1":18.43,"balDisp":42.83,"dispLen":217.64,"designer":"Warren Metcalf","builder":"South Coast Seacraft Co. (USA)","construction":"FG","balType":null,"firstBuilt":"1969","lastBuilt":null,"numBuilt":100},"rigSail":{"i_ig":{"feet":30.5,"meters":9.3},"j":{"feet":9,"meters":2.74},"p":{"feet":27,"meters":8.23},"e":{"feet":12,"meters":3.66},"py":null,"ey":null,"isp":null,"spl_tps":null,"saFore":{"feet":137.25,"meters":12.75},"saMain":{"feet":162,"meters":15.05},"sailArea":{"feet":299.25,"meters":27.8},"sailAreaDisp2":18.44,"estForestayLength":{"feet":31.8,"meters":9.69}},"buildersPastPresent":[{"href":"view_builder.asp?builder_id=42","title":"South Coast Seacraft Co."}]}
