{"name":"SWING 28","images":[{"alt":"Swing 28 photo on sailboatdata.com","src":"imagehelper.asp?file_id=4400","type":"photo"},{"alt":"Swing 28 drawing on sailboatdata.com","src":"imagehelper.asp?file_id=4472","type":"drawing"}],"basics":{"hullType":"Fin w/spade rudder","rigType":"Fractional  Sloop","loa":{"feet":27.49,"meters":8.38},"lwl":{"feet":23.29,"meters":7.1},"beam":{"feet":9.58,"meters":2.92},"listedSa":{"feet":352,"meters":32.7},"draftMax":{"feet":4.96,"meters":1.51},"draftMin":null,"displacement":1844,"ballast":null,"sailAreaDisp1":22.17,"balDisp":null,"dispLen":143.65,"designer":"Bruce Farr","builder":null,"construction":"FG","balType":null,"firstBuilt":"1987","lastBuilt":null,"numBuilt":null},"rigSail":{"i_ig":{"feet":30.25,"meters":9.22},"j":{"feet":9.45,"meters":2.88},"p":{"feet":32.68,"meters":9.96},"e":{"feet":12.8,"meters":3.9},"py":null,"ey":null,"isp":null,"spl_tps":null,"saFore":{"feet":142.93,"meters":13.28},"saMain":{"feet":209.15,"meters":19.43},"sailArea":{"feet":352.08,"meters":32.71},"sailAreaDisp2":22.18,"estForestayLength":{"feet":31.69,"meters":9.66}},"designer":[{"href":"view_designer.asp?designer_id=17","title":"Bruce Farr"}],"notes":"Farr design #189."}
