{"name":"BANNER 41","images":[],"basics":{"hullType":"Fin w/spade rudder","rigType":"Fractional  Sloop","loa":{"feet":40.52,"meters":12.35},"lwl":{"feet":32.81,"meters":10},"beam":{"feet":10.7,"meters":3.26},"listedSa":{"feet":766,"meters":71.16},"draftMax":{"feet":6.07,"meters":1.85},"draftMin":null,"displacement":5500,"ballast":2350,"sailAreaDisp1":23.3,"balDisp":42.73,"dispLen":153.26,"designer":"Ib Hauge Nielsen","builder":null,"construction":"FG","balType":"Lead","firstBuilt":"1979","lastBuilt":null,"numBuilt":null},"auxPower":{"make":"Yanmar","model":null,"type":"Diesel","hp":"18"},"rigSail":{"i_ig":{"feet":44.95,"meters":13.7},"j":{"feet":13.98,"meters":4.26},"p":{"feet":49.21,"meters":15},"e":{"feet":18.37,"meters":5.6},"py":null,"ey":null,"isp":null,"spl_tps":null,"saFore":{"feet":314.2,"meters":29.19},"saMain":{"feet":451.99,"meters":41.99},"sailArea":{"feet":766.19,"meters":71.18},"sailAreaDisp2":23.31,"estForestayLength":{"feet":47.07,"meters":14.35}},"designer":[{"href":"view_designer.asp?designer_id=354","title":"Ib Hauge Nielsen"}]}
