{"name":"CONTEST 40S","images":[{"alt":"Contest 40S drawing on sailboatdata.com","src":"imagehelper.asp?file_id=9566","type":"drawing"}],"basics":{"hullType":"Fin with rudder on skeg","rigType":"Masthead Sloop","loa":{"feet":39.67,"meters":12.09},"lwl":{"feet":30.8,"meters":9.39},"beam":{"feet":12.67,"meters":3.86},"listedSa":{"feet":767,"meters":71.25},"draftMax":{"feet":5.5,"meters":1.68},"draftMin":null,"displacement":11794,"ballast":4536,"sailAreaDisp1":14.04,"balDisp":38.46,"dispLen":397.26,"designer":"Dick Zaal","builder":"Conyplex","construction":"FG","balType":null,"firstBuilt":"1993","lastBuilt":"1997","numBuilt":30},"rigSail":{"i_ig":{"feet":55.45,"meters":16.9},"j":{"feet":15.58,"meters":4.75},"p":{"feet":48.56,"meters":14.8},"e":{"feet":13.78,"meters":4.2},"py":null,"ey":null,"isp":null,"spl_tps":null,"saFore":{"feet":431.96,"meters":40.13},"saMain":{"feet":334.58,"meters":31.08},"sailArea":{"feet":766.53,"meters":71.21},"sailAreaDisp2":14.03,"estForestayLength":{"feet":57.6,"meters":17.56}},"buildersPastPresent":[{"href":"view_builder.asp?builder_id=163","title":"Contest Yachts - Conyplex"}],"designer":[{"href":"view_designer.asp?designer_id=167","title":"Dick Zaal"}]}
