{"name":"CONTEST 25-1","images":[{"alt":"Contest 25-1 photo on sailboatdata.com","src":"imagehelper.asp?file_id=4813","type":"photo"},{"alt":"Contest 25-1 drawing on sailboatdata.com","src":"imagehelper.asp?file_id=4812","type":"drawing"}],"basics":{"hullType":"Fin Keel","rigType":"Masthead Sloop","loa":{"feet":25,"meters":7.62},"lwl":{"feet":20.8,"meters":6.34},"beam":{"feet":7.22,"meters":2.2},"listedSa":null,"draftMax":{"feet":3.94,"meters":1.2},"draftMin":null,"displacement":2495,"ballast":907,"sailAreaDisp1":null,"balDisp":36.35,"dispLen":272.85,"designer":"G. Luyten","builder":"Coniplex","construction":"FG","balType":null,"firstBuilt":"1959","lastBuilt":"1969","numBuilt":300},"auxPower":{"make":"Volvo","model":"MD 2010","type":"Diesel","hp":null},"tanks":{"water":"26 gals. /  98 ltrs.","fuel":"10 gals. /  38 ltrs."},"buildersPastPresent":[{"href":"view_builder.asp?builder_id=163","title":"Contest Yachts - Conyplex"}]}
