{"name":"BOSUN 14","images":[{"alt":"Bosun Dinghy photo on sailboatdata.com","src":"imagehelper.asp?file_id=4842","type":"photo"}],"basics":{"hullType":"Centerboard Dinghy","rigType":"Fractional  Sloop","loa":{"feet":14,"meters":4.27},"lwl":null,"beam":{"feet":5.51,"meters":1.68},"listedSa":{"feet":111,"meters":10.31},"draftMax":{"feet":4.49,"meters":1.37},"draftMin":null,"displacement":168,"ballast":null,"sailAreaDisp1":34.5,"balDisp":null,"dispLen":null,"designer":"Ian Proctor","builder":"Bossoms Boatyard (UK)","construction":"FG","balType":null,"firstBuilt":"1963","lastBuilt":null,"numBuilt":null},"buildersPastPresent":[{"href":"view_builder.asp?builder_id=424","title":"Bossoms Boatyard"}],"designer":[{"href":"view_designer.asp?designer_id=105","title":"Ian Proctor"}],"notes":"Designed originally as a trainer for the Royal Navy.\r\nThere was a class web site which has now disappeared."}
