{"name":"NICHOLSON 36","images":[],"basics":{"hullType":"Fin Keel","rigType":"Masthead Sloop","loa":{"feet":36.25,"meters":11.05},"lwl":{"feet":26,"meters":7.92},"beam":{"feet":9.5,"meters":2.9},"listedSa":{"feet":565,"meters":52.49},"draftMax":{"feet":5.92,"meters":1.8},"draftMin":null,"displacement":7643,"ballast":null,"sailAreaDisp1":13.81,"balDisp":null,"dispLen":427.99,"designer":"Charles A. Nicholson/ Peter Nicholson","builder":"Camper & Nicholson","construction":"FG","balType":"Lead","firstBuilt":"1960","lastBuilt":null,"numBuilt":26},"buildersPastPresent":[{"href":"view_builder.asp?builder_id=71","title":"Halmatic Ltd."},{"href":"view_builder.asp?builder_id=96","title":"Camper & Nicholson"}],"designer":[{"href":"view_designer.asp?designer_id=308","title":"Charles A. Nicholson"}],"seeAlso":{"relatedBoat":{"href":"viewrecord.asp?class_id=5120","title":"JOLINA 35"}},"notes":"The first boat with a fiberglass hull, built by Camper & Nicholson. The structural integrity of the new material was, at the time, uncertain, so alloy frames were added. Designed by Peter Nicholson though strongly influenced by the very successful JOLINA 35, by Charles Nicholson."}
