{"name":"STARWIND 15","images":[],"basics":{"hullType":"Centerboard Dinghy","rigType":"Fractional  Sloop","loa":{"feet":15,"meters":4.57},"lwl":{"feet":14.08,"meters":4.29},"beam":{"feet":6,"meters":1.83},"listedSa":{"feet":150,"meters":13.93},"draftMax":{"feet":4.08,"meters":1.24},"draftMin":{"feet":0.67,"meters":0.2},"displacement":186,"ballast":null,"sailAreaDisp1":43.54,"balDisp":null,"dispLen":65.57,"designer":"Rod Macalpine-Downie/Dick Gibbs","builder":"Wellcraft Marine (USA)","construction":"FG","balType":null,"firstBuilt":"1984","lastBuilt":"1987","numBuilt":null},"buildersPastPresent":[{"href":"view_builder.asp?builder_id=573","title":"Starwind (USA)"}],"designer":[{"href":"view_designer.asp?designer_id=149","title":"J.R. (Rod) Macalpine-Downie"},{"href":"view_designer.asp?designer_id=339","title":"Dick Gibbs"}],"seeAlso":{"relatedBoat":{"href":"viewrecord.asp?class_id=3755","title":"MUTINEER 15"}},"notes":"Known primarily as the MUTINEER 15. (see MUTINEER 15)\r\nSail area(sq.ft.):\r\nTotal-150, Main-100, Jib-50, Spinnaker-166\r\nPRODUCTION HISTORY:\r\n1971 - 1980\r\nChrysler Corp. built almost 8,000. In 1980 the Chrysler sailboat division is sold to Texas Marine Industries, (TMI). \r\n1981-1982\r\nTexas Marine Industries, (TMI). \r\n1982 - 1984\r\nWellcraft Marine (AKA STARWIND 15)\r\n1984 - 1987\r\nGloucester Yachts (some as the GLOUCESTER 15)\r\n1987 - 2003\r\nCardinal Yachts builds a small number. \r\n2003 -      \r\nNickels Boats (current builder)"}
