{"name":"CAPRI 14 (SCHOCK)","images":[{"alt":"Capri 14 (Schock) photo on sailboatdata.com","src":"imagehelper.asp?file_id=8807","type":"photo"},{"alt":"Capri 14 (Schock) drawing on sailboatdata.com","src":"imagehelper.asp?file_id=8808","type":"drawing"}],"basics":{"hullType":"Fin w/transom hung rudder","rigType":"Fractional  Sloop","loa":{"feet":14,"meters":4.27},"lwl":null,"beam":{"feet":6,"meters":1.83},"listedSa":null,"draftMax":{"feet":2.16,"meters":0.66},"draftMin":null,"displacement":238,"ballast":113,"sailAreaDisp1":null,"balDisp":47.48,"dispLen":null,"designer":"Lehman/W. D. Schock","builder":"W. D Schock","construction":"FG","balType":null,"firstBuilt":"1960","lastBuilt":null,"numBuilt":null},"buildersPastPresent":[{"href":"view_builder.asp?builder_id=39","title":"Schock W.D."}],"seeAlso":{"relatedBoat":{"href":"viewrecord.asp?class_id=6229","title":"HARBOR 14 (SCHOCK)"}},"notes":"A keel version of the LIDO 14. Later known as the HARBOR 14."}
