{"name":"ALO MIKKEL 26","images":[],"basics":{"hullType":"Fin with rudder on skeg","rigType":"Masthead Sloop","loa":{"feet":25.26,"meters":7.7},"lwl":{"feet":21,"meters":6.4},"beam":{"feet":8.96,"meters":2.73},"listedSa":{"feet":286,"meters":26.57},"draftMax":{"feet":5.09,"meters":1.55},"draftMin":null,"displacement":2700,"ballast":1120,"sailAreaDisp1":13.98,"balDisp":41.48,"dispLen":286.92,"designer":"Freddy Mikkelsen","builder":"Alo Yachts (NOR)","construction":"FG","balType":"Iron","firstBuilt":"1977","lastBuilt":"1980","numBuilt":300},"auxPower":{"make":"Volvo Penta","model":"MD5A","type":"Diesel","hp":"7.5"},"rigSail":{"i_ig":{"feet":32.81,"meters":10},"j":{"feet":10.17,"meters":3.1},"p":{"feet":29.76,"meters":9.07},"e":{"feet":8.01,"meters":2.44},"py":null,"ey":null,"isp":null,"spl_tps":null,"saFore":{"feet":166.84,"meters":15.5},"saMain":{"feet":119.19,"meters":11.07},"sailArea":{"feet":286.03,"meters":26.57},"sailAreaDisp2":13.98,"estForestayLength":{"feet":34.35,"meters":10.47}},"buildersPastPresent":[{"href":"view_builder.asp?builder_id=130","title":"Alo Yachts (NOR)"}]}
