{"name":"TAIPAN 28","images":[{"alt":"Taipan 28 photo on sailboatdata.com","src":"imagehelper.asp?file_id=7710","type":"photo"}],"basics":{"hullType":"Long Keel","rigType":"Masthead Sloop","loa":{"feet":28,"meters":8.53},"lwl":{"feet":20.75,"meters":6.32},"beam":{"feet":7.75,"meters":2.36},"listedSa":{"feet":338,"meters":31.4},"draftMax":{"feet":4.5,"meters":1.37},"draftMin":null,"displacement":3561,"ballast":1390,"sailAreaDisp1":13.74,"balDisp":39.03,"dispLen":392.25,"designer":"Newell","builder":"Interchem Engineers Ltd. (HK)","construction":"FG","balType":"Iron","firstBuilt":"1970","lastBuilt":"1980","numBuilt":80},"auxPower":{"make":"Volvo Penta","model":"MD1B","type":"Diesel","hp":"10"},"tanks":{"water":"23 gals. /  87 ltrs.","fuel":"9 gals. /  34 ltrs."},"designer":[{"href":"view_designer.asp?designer_id=172","title":"G. Taylor Newell"}],"seeAlso":{"relatedBoat":{"href":"viewrecord.asp?class_id=560","title":"NEWELL CADET"}},"notes":"It seems nearly certain that TAIPAN 28 shares the same hull as the NEWELL CADET (aka OFFSHORE 27), built by Cheoy Lee Shipyard, HK. Interchem Engineers Ltd. was located at Pak Sha Wan, outside Sai Kung (HK). \r\nThanks to Mark Warburton, among others, for providing additional information on this yacht."}
