{"name":"FALCON 35 (WESTERLY)","images":[],"basics":{"hullType":"Fin w/spade rudder","rigType":"Masthead Sloop","loa":{"feet":34.58,"meters":10.54},"lwl":{"feet":27,"meters":8.23},"beam":{"feet":12.25,"meters":3.73},"listedSa":{"feet":540,"meters":50.17},"draftMax":{"feet":4.92,"meters":1.5},"draftMin":null,"displacement":6387,"ballast":2954,"sailAreaDisp1":14.87,"balDisp":46.25,"dispLen":319.35,"designer":"Ed Dubois","builder":"Westerly Marine Ltd. (UK)","construction":"FG","balType":null,"firstBuilt":"1988","lastBuilt":"1990","numBuilt":19},"auxPower":{"make":"Volvo","model":null,"type":"Diesel","hp":null},"tanks":{"water":"77 gals. /  291 ltrs.","fuel":"42 gals. /  159 ltrs."},"buildersPastPresent":[{"href":"view_builder.asp?builder_id=46","title":"Westerly Marine Construction Ltd."}],"designer":[{"href":"view_designer.asp?designer_id=106","title":"Ed Dubois"}],"notes":"Twin and fin keels versions were available.\r\nDraft for twin keel verson: 3.92'."}
