{"name":"NAUTOR 50","images":[{"alt":"Nautor 50 drawing on sailboatdata.com","src":"imagehelper.asp?file_id=8032","type":"drawing"}],"basics":{"hullType":"Fin with rudder on skeg","rigType":"Masthead  Ketch","loa":{"feet":49.7,"meters":15.15},"lwl":{"feet":37.5,"meters":11.43},"beam":{"feet":15.09,"meters":4.6},"listedSa":{"feet":1112,"meters":103.3},"draftMax":{"feet":5.58,"meters":1.7},"draftMin":null,"displacement":23100,"ballast":6600,"sailAreaDisp1":13.01,"balDisp":28.57,"dispLen":431.12,"designer":"S&S","builder":"Nautor","construction":"FG","balType":"Lead","firstBuilt":"1976","lastBuilt":"1978","numBuilt":9},"auxPower":{"make":"Perkins","model":null,"type":"Diesel","hp":"115"},"tanks":{"water":"523 gals. /  1980 ltrs.","fuel":"470 gals. /  1779 ltrs."},"rigSail":{"i_ig":{"feet":59,"meters":17.98},"j":{"feet":19.91,"meters":6.07},"p":{"feet":51.25,"meters":15.62},"e":{"feet":14.5,"meters":4.42},"py":{"feet":32.3,"meters":9.85},"ey":{"feet":9.5,"meters":2.9},"isp":null,"spl_tps":null,"saFore":{"feet":587.35,"meters":54.56},"saMain":{"feet":371.56,"meters":34.52},"sailArea":{"feet":1,"meters":103.34},"sailAreaDisp2":13.01,"estForestayLength":{"feet":62.27,"meters":18.98}},"buildersPastPresent":[{"href":"view_builder.asp?builder_id=104","title":"Nautor (Swan sailboats)"}],"designer":[{"href":"view_designer.asp?designer_id=12","title":"Sparkman & Stephens"}],"notes":"Also called SWAN 50 MS.\r\nMolds were later sold to Siltala Yachts that built a modified version called the NAUTICAL 52."}
