{"name":"PRIVILEGE 585","images":[{"alt":"Privilege 585 drawing on sailboatdata.com","src":"imagehelper.asp?file_id=8925","type":"drawing"}],"basics":{"hullType":"Catamaran Twin Keel","rigType":"Fractional  Sloop","loa":{"feet":55.75,"meters":16.99},"lwl":{"feet":55,"meters":16.76},"beam":{"feet":30.33,"meters":9.24},"listedSa":{"feet":2110,"meters":196.02},"draftMax":{"feet":5.75,"meters":1.75},"draftMin":null,"displacement":17781,"ballast":null,"sailAreaDisp1":29.38,"balDisp":null,"dispLen":105.18,"designer":"Marc Lombard","builder":"Alliaura Marine (France)","construction":"FG","balType":null,"firstBuilt":"2002","lastBuilt":"2005","numBuilt":null},"auxPower":{"make":"Yanmar","model":null,"type":"Diesel x 2","hp":"22"},"tanks":{"water":"317 gals. /  1200 ltrs.","fuel":"370 gals. /  1400 ltrs.","mastHeightFromDwl":"88.92' /  27.10m"},"buildersPastPresent":[{"href":"view_builder.asp?builder_id=160","title":"Privilege Catamarans"}],"designer":[{"href":"view_designer.asp?designer_id=157","title":"Marc Lombard"}]}
