{"name":"SUN FAST 41 (JEANNEAU)","images":[{"alt":"Sun Fast 41 (Jeanneau) drawing on sailboatdata.com","src":"imagehelper.asp?file_id=9092","type":"drawing"}],"basics":{"hullType":"Fin w/spade rudder","rigType":"Masthead Sloop","loa":{"feet":40.85,"meters":12.45},"lwl":{"feet":32.74,"meters":9.98},"beam":{"feet":12.93,"meters":3.94},"listedSa":{"feet":703,"meters":65.31},"draftMax":{"feet":6.4,"meters":1.95},"draftMin":null,"displacement":7300,"ballast":2555,"sailAreaDisp1":17.71,"balDisp":35,"dispLen":204.73,"designer":"Doug Peterson","builder":"Jeanneau (FRA)","construction":"FG","balType":null,"firstBuilt":"1990","lastBuilt":null,"numBuilt":null},"auxPower":{"make":"Yanmar","model":null,"type":"Diesel","hp":null},"tanks":{"water":"27 gals. /  102 ltrs.","fuel":"33 gals. /  125 ltrs."},"rigSail":{"i_ig":{"feet":51.18,"meters":15.6},"j":{"feet":15.09,"meters":4.6},"p":{"feet":44.95,"meters":13.7},"e":{"feet":14.11,"meters":4.3},"py":null,"ey":null,"isp":null,"spl_tps":null,"saFore":{"feet":386.15,"meters":35.87},"saMain":{"feet":317.12,"meters":29.46},"sailArea":{"feet":703.28,"meters":65.33},"sailAreaDisp2":17.72,"estForestayLength":{"feet":53.36,"meters":16.26}},"buildersPastPresent":[{"href":"view_builder.asp?builder_id=48","title":"Jeanneau (FRA)"}],"designer":[{"href":"view_designer.asp?designer_id=27","title":"Doug Peterson"}],"notes":"Keel/Centerboard vers: BU: 1.47m/4.82'  BD: 2.18m/5.15'\r\nDisp: 7360 kg/16226 lbs.\r\nIt is likely that this is another version of the SUN LEGENDE 41."}
