{"name":"TARTAN 4700","images":[{"alt":"Tartan 4700 drawing on sailboatdata.com","src":"imagehelper.asp?file_id=9195","type":"drawing"}],"basics":{"hullType":"Fin w/spade rudder","rigType":"Fractional  Sloop","loa":{"feet":47,"meters":14.33},"lwl":{"feet":39,"meters":11.89},"beam":{"feet":14.08,"meters":4.29},"listedSa":{"feet":1038,"meters":96.43},"draftMax":{"feet":6.25,"meters":1.91},"draftMin":null,"displacement":12701,"ballast":4423,"sailAreaDisp1":18.08,"balDisp":34.82,"dispLen":210.73,"designer":"Tim Jackett","builder":"Tartan Marine","construction":"FG","balType":"Lead","firstBuilt":"2011","lastBuilt":null,"numBuilt":null},"tanks":{"water":"200 gals. /  757 ltrs.","fuel":"80 gals. /  303 ltrs."},"rigSail":{"i_ig":{"feet":59.5,"meters":18.14},"j":{"feet":16.5,"meters":5.03},"p":{"feet":57,"meters":17.37},"e":{"feet":19.2,"meters":5.85},"py":null,"ey":null,"isp":null,"spl_tps":null,"saFore":{"feet":490.88,"meters":45.6},"saMain":{"feet":547.2,"meters":50.83},"sailArea":{"feet":1,"meters":96.44},"sailAreaDisp2":18.09,"estForestayLength":{"feet":61.75,"meters":18.82}},"buildersPastPresent":[{"href":"view_builder.asp?builder_id=156","title":"Tartan Marine"}],"designer":[{"href":"view_designer.asp?designer_id=242","title":"Tim Jackett"}]}
