{"name":"MYSTERY 30","images":[],"basics":{"hullType":"Fin w/bulb & spade rudder","rigType":"Fractional  Sloop","loa":{"feet":30.61,"meters":9.33},"lwl":{"feet":22.7,"meters":6.92},"beam":{"feet":8.53,"meters":2.6},"listedSa":{"feet":415,"meters":38.55},"draftMax":{"feet":5.74,"meters":1.75},"draftMin":null,"displacement":2700,"ballast":1270,"sailAreaDisp1":20.28,"balDisp":47.04,"dispLen":227.16,"designer":"David Thomas","builder":"Cornish Crabbers Ltd. (UK)","construction":"FG","balType":"Iron","firstBuilt":"2010","lastBuilt":null,"numBuilt":null},"auxPower":{"make":"Yanmar","model":null,"type":"Diesel","hp":null},"buildersPastPresent":[{"href":"view_builder.asp?builder_id=393","title":"Cornish Crabbers"}],"designer":[{"href":"view_designer.asp?designer_id=76","title":"David Thomas"}],"seeAlso":{"relatedBoat":{"href":"viewrecord.asp?class_id=7277","title":"LINK 30"}},"notes":"Originally called the LINK 30."}
