{"name":"CONSER 47","images":[{"alt":"Conser 47 drawing on sailboatdata.com","src":"imagehelper.asp?file_id=9758","type":"drawing"}],"basics":{"hullType":"Catamaran Twin Dbrd.","rigType":"Frac. Sloop (Rotating Spar)","loa":{"feet":47,"meters":14.33},"lwl":{"feet":45,"meters":13.72},"beam":{"feet":24,"meters":7.32},"listedSa":{"feet":1065,"meters":98.94},"draftMax":{"feet":3.75,"meters":1.14},"draftMin":{"feet":1.2,"meters":0.37},"displacement":5443,"ballast":null,"sailAreaDisp1":32.62,"balDisp":null,"dispLen":58.79,"designer":"John Conser","builder":"Conser Catamaran (USA)","construction":"FG","balType":null,"firstBuilt":"1992","lastBuilt":"2002","numBuilt":null},"tanks":{"water":"90 gals. /  341 ltrs.","fuel":"30 gals. /  114 ltrs."},"notes":"High performance catamaran with cruising accommodations.\r\nWing spar available as an option."}
