{"name":"SOUTHERLY 38","images":[{"alt":"Southerly 38 photo on sailboatdata.com","src":"imagehelper.asp?file_id=9855","type":"photo"}],"basics":{"hullType":"Swing Keel","rigType":"Fractional  Sloop","loa":{"feet":39.33,"meters":11.99},"lwl":{"feet":36,"meters":10.97},"beam":{"feet":13,"meters":3.96},"listedSa":{"feet":770,"meters":71.53},"draftMax":{"feet":8.5,"meters":2.59},"draftMin":{"feet":2.67,"meters":0.81},"displacement":9921,"ballast":3802,"sailAreaDisp1":15.81,"balDisp":38.32,"dispLen":209.28,"designer":"Stephen Jones","builder":"Northshore Yachts","construction":"FG","balType":null,"firstBuilt":"2008","lastBuilt":null,"numBuilt":null},"auxPower":{"make":"Yanmar","model":null,"type":"Diesel","hp":"40"},"tanks":{"water":"59 gals. /  223 ltrs.","fuel":"54 gals. /  204 ltrs.","mastHeightFromDwl":"61.83' /  18.85m"},"buildersPastPresent":[{"href":"view_builder.asp?builder_id=150","title":"Northshore Yachts (UK)"}],"designer":[{"href":"view_designer.asp?designer_id=137","title":"Stephen Jones"}],"notes":"A fixed keel version also available.\r\nDraft: 6.33'/1.93m"}
