{"name":"GRAND SURPISE","images":[{"alt":"Grand Surprise 31 photo on sailboatdata.com","src":"imagehelper.asp?file_id=10232","type":"photo"},{"alt":"Grand Surprise 31 drawing on sailboatdata.com","src":"imagehelper.asp?file_id=10233","type":"drawing"}],"basics":{"hullType":"Fin w/bulb & spade rudder","rigType":"Fractional  Sloop","loa":{"feet":31.3,"meters":9.54},"lwl":{"feet":29.3,"meters":8.93},"beam":{"feet":9.78,"meters":2.98},"listedSa":{"feet":544,"meters":50.54},"draftMax":{"feet":6.73,"meters":2.05},"draftMin":null,"displacement":2650,"ballast":1050,"sailAreaDisp1":26.91,"balDisp":39.62,"dispLen":103.68,"designer":"Joubert & Nivelt","builder":"Archambault (FRA)","construction":"FG","balType":null,"firstBuilt":"1999","lastBuilt":null,"numBuilt":null},"auxPower":{"make":"Lombardini","model":null,"type":"Diesel","hp":null},"rigSail":{"i_ig":{"feet":40.29,"meters":12.28},"j":{"feet":11.19,"meters":3.41},"p":{"feet":43.14,"meters":13.15},"e":{"feet":14.76,"meters":4.5},"py":null,"ey":null,"isp":null,"spl_tps":null,"saFore":{"feet":225.42,"meters":20.94},"saMain":{"feet":318.37,"meters":29.58},"sailArea":{"feet":543.8,"meters":50.52},"sailAreaDisp2":26.9,"estForestayLength":{"feet":41.82,"meters":12.75}},"buildersPastPresent":[{"href":"view_builder.asp?builder_id=218","title":"Archambault Boats (FRA)"}],"designer":[{"href":"view_designer.asp?designer_id=119","title":"Joubert-Nivelt"}],"relatedLinks":[{"href":"http://www.grandsurprise.com","title":"Grand Surprise Class (FRA)"}]}
