{"name":"S2 27","images":[{"alt":"S2 27 photo on sailboatdata.com","src":"imagehelper.asp?file_id=7861","type":"photo"},{"alt":"S2 27 drawing on sailboatdata.com","src":"imagehelper.asp?file_id=7860","type":"drawing"}],"basics":{"hullType":"Fin w/transom hung rudder","rigType":"Masthead Sloop","loa":{"feet":26.58,"meters":8.1},"lwl":{"feet":23.33,"meters":7.11},"beam":{"feet":9.25,"meters":2.82},"listedSa":{"feet":342,"meters":31.77},"draftMax":{"feet":4.75,"meters":1.45},"draftMin":null,"displacement":2268,"ballast":953,"sailAreaDisp1":18.77,"balDisp":42.02,"dispLen":175.78,"designer":null,"builder":"S-2 Yachts","construction":"FG","balType":null,"firstBuilt":"1985","lastBuilt":"1987","numBuilt":85},"rigSail":{"i_ig":{"feet":34,"meters":10.36},"j":{"feet":10,"meters":3.05},"p":{"feet":28.67,"meters":8.74},"e":{"feet":12,"meters":3.66},"py":null,"ey":null,"isp":null,"spl_tps":null,"saFore":{"feet":170,"meters":15.79},"saMain":{"feet":172.02,"meters":15.98},"sailArea":{"feet":342.02,"meters":31.77},"sailAreaDisp2":18.77,"estForestayLength":{"feet":35.44,"meters":10.8}},"buildersPastPresent":[{"href":"view_builder.asp?builder_id=143","title":"S2 Yachts (USA)"}]}
