{"name":"NACRA 17","images":[{"alt":"NACRA 17 Olympic photo on sailboatdata.com","src":"imagehelper.asp?file_id=10481","type":"photo"},{"alt":"NACRA 17 Olympic drawing on sailboatdata.com","src":"imagehelper.asp?file_id=10480","type":"drawing"}],"basics":{"hullType":"Catamaran Twin Dbrd.","rigType":"Frac. Sloop (Rotating Spar)","loa":{"feet":17.22,"meters":5.25},"lwl":null,"beam":{"feet":8.5,"meters":2.59},"listedSa":{"feet":216,"meters":20.07},"draftMax":{"feet":3.4,"meters":1.04},"draftMin":{"feet":0.4,"meters":0.12},"displacement":138,"ballast":null,"sailAreaDisp1":76.52,"balDisp":null,"dispLen":null,"designer":"Morrelli & Melvin","builder":"NACRA","construction":"GRP carbon epoxy","balType":null,"firstBuilt":"2012","lastBuilt":null,"numBuilt":null},"rigSail":{"i_ig":{"feet":29.86,"meters":9.1},"j":null,"p":null,"e":null,"py":null,"ey":null,"isp":null,"spl_tps":null},"buildersPastPresent":[{"href":"view_builder.asp?builder_id=293","title":"NACRA Catamarans"}],"designer":[{"href":"view_designer.asp?designer_id=391","title":"Morrelli & Melvin"},{"href":"http://www.nacra17class.com","title":"www.nacra17class.com"}],"notes":"Carbon mast and carbon epoxy GRP high aspect curved daggerboards.\r\nSpin. Area 19m2\r\nSelected as 2 person catamaran class for 2016 Olympics."}
