{"name":"WIBO 990","images":[{"alt":"Wibo 990 drawing on sailboatdata.com","src":"imagehelper.asp?file_id=11144","type":"drawing"}],"basics":{"hullType":"Fin w/spade rudder","rigType":"Fractional  Sloop","loa":{"feet":32.5,"meters":9.91},"lwl":{"feet":26.5,"meters":8.08},"beam":{"feet":11,"meters":3.35},"listedSa":{"feet":575,"meters":53.42},"draftMax":{"feet":5.25,"meters":1.6},"draftMin":null,"displacement":5300,"ballast":1970,"sailAreaDisp1":17.93,"balDisp":37.17,"dispLen":280.29,"designer":"E. G. van de Stadt","builder":"Jachtwerft G. van Wijk & Zoon (NED)","construction":"Steel (multichine)","balType":"Iron","firstBuilt":"1984","lastBuilt":null,"numBuilt":null},"auxPower":{"make":"Bukh","model":null,"type":"Diesel","hp":"20"},"buildersPastPresent":[{"href":"view_builder.asp?builder_id=146","title":"Wibo Yachts"}],"designer":[{"href":"view_designer.asp?designer_id=35","title":"E. G. Van de Stadt"}],"notes":"Shoal draft: 4.25'"}
