{"name":"SAN CLEMENTE 23","images":[],"basics":{"hullType":"Fin with rudder on skeg","rigType":"Masthead Sloop","loa":{"feet":23,"meters":7.01},"lwl":{"feet":20.08,"meters":6.12},"beam":{"feet":8,"meters":2.44},"listedSa":{"feet":257,"meters":23.88},"draftMax":{"feet":3.83,"meters":1.17},"draftMin":null,"displacement":1406,"ballast":null,"sailAreaDisp1":19.39,"balDisp":null,"dispLen":170.93,"designer":"William Crealock","builder":"South Coast Fiberglass Products (USA)","construction":"FG","balType":null,"firstBuilt":"1969","lastBuilt":null,"numBuilt":null},"rigSail":{"i_ig":{"feet":27,"meters":8.23},"j":{"feet":10.5,"meters":3.2},"p":{"feet":23,"meters":7.01},"e":{"feet":10,"meters":3.05},"py":null,"ey":null,"isp":null,"spl_tps":null,"saFore":{"feet":141.75,"meters":13.17},"saMain":{"feet":115,"meters":10.68},"sailArea":{"feet":256.75,"meters":23.85},"sailAreaDisp2":19.37,"estForestayLength":{"feet":28.97,"meters":8.83}},"designer":[{"href":"view_designer.asp?designer_id=103","title":"William Crealock"}],"notes":"Extremely Rare. Photo has been promised.\r\nSouth Coast Fiberglass Products was located at San Clemente CA."}
