{"name":"SOUTHERN CROSS 28","images":[{"alt":"Southern Cross 28 photo on sailboatdata.com","src":"imagehelper.asp?file_id=5417","type":"photo"},{"alt":"Southern Cross 28 drawing on sailboatdata.com","src":"imagehelper.asp?file_id=8019","type":"drawing"}],"basics":{"hullType":"Fin with rudder on skeg","rigType":"Cutter","loa":{"feet":30.42,"meters":9.27},"lwl":{"feet":20.17,"meters":6.15},"beam":{"feet":8.5,"meters":2.59},"listedSa":{"feet":415,"meters":38.55},"draftMax":{"feet":4.67,"meters":1.42},"draftMin":null,"displacement":3856,"ballast":1542,"sailAreaDisp1":15.99,"balDisp":39.99,"dispLen":462.44,"designer":"Thomas Gilmer","builder":"C. E. Ryder (USA)","construction":"FG","balType":"Lead","firstBuilt":"1978","lastBuilt":null,"numBuilt":null},"rigSail":{"i_ig":{"feet":34.8,"meters":10.61},"j":{"feet":13,"meters":3.96},"p":{"feet":31,"meters":9.45},"e":{"feet":12.2,"meters":3.72},"py":null,"ey":null,"isp":null,"spl_tps":null,"saFore":{"feet":226.2,"meters":21.01},"saMain":{"feet":189.1,"meters":17.57},"sailArea":{"feet":415.3,"meters":38.58},"sailAreaDisp2":16.01,"estForestayLength":{"feet":37.15,"meters":11.32}},"buildersPastPresent":[{"href":"view_builder.asp?builder_id=247","title":"C. E. Ryder"}],"designer":[{"href":"view_designer.asp?designer_id=2","title":"Thomas Gillmer"}],"notes":"Also called GILMER 28."}
